examples/__init__.py
examples/fx_currency_rates.py
examples/generate_rsa_keys.py
kuveytturk/__init__.py
kuveytturk/api.py
kuveytturk/auth.py
kuveytturk/binder.py
kuveytturk/error.py
kuveytturk/models.py
kuveytturk/parsers.py
kuveytturk/utils.py
kuveytturk-1.0.1.dist-info/LICENSE
kuveytturk-1.0.1.dist-info/METADATA
kuveytturk-1.0.1.dist-info/WHEEL
kuveytturk-1.0.1.dist-info/top_level.txt
kuveytturk-1.0.1.dist-info/RECORD
