Metadata-Version: 2.1
Name: kuveytturk
Version: 1.0.1
Summary: A Python wrapper for the Kuveyt Turk API
Home-page: https://github.com/iuysal/kuveytturk
Author: Ibrahim Uysal
License: UNKNOWN
Keywords: twitter library
Platform: UNKNOWN
Classifier: License :: OSI Approved :: MIT License
Classifier: Operating System :: OS Independent
Classifier: Topic :: Software Development :: Libraries
Classifier: Programming Language :: Python :: 3
Classifier: Programming Language :: Python :: 3.4
Classifier: Programming Language :: Python :: 3.5
Classifier: Programming Language :: Python :: 3.6
Requires-Python: >=2.7, !=3.0.*, !=3.1.*, !=3.2.*, !=3.3.*
Requires-Dist: six (>=1.12.0)
Requires-Dist: requests (>=2.21.0)
Requires-Dist: pycrypto (>=2.6.1)
